skdiveMove/__init__.py
skdiveMove/__main__.py
skdiveMove/calibconfig.py
skdiveMove/calibspeed.py
skdiveMove/core.py
skdiveMove/helpers.py
skdiveMove/metadata.py
skdiveMove/plotting.py
skdiveMove/tdr.py
skdiveMove/tdrphases.py
skdiveMove/tdrsource.py
skdiveMove/zoc.py
skdiveMove/bouts/__init__.py
skdiveMove/bouts/bouts.py
skdiveMove/bouts/boutsmle.py
skdiveMove/bouts/boutsnls.py
skdiveMove/config_examples/ag_mk7_2002_022_config.json
skdiveMove/imutools/__init__.py
skdiveMove/imutools/allan.py
skdiveMove/imutools/ellipsoid.py
skdiveMove/imutools/imu.py
skdiveMove/imutools/imu2body.py
skdiveMove/imutools/imucalibrate.py
skdiveMove/imutools/vector.py
skdiveMove/tests/__init__.py
skdiveMove/tests/get_sample_data.py
skdiveMove/tests/test_BoutsMLE.py
skdiveMove/tests/test_BoutsNLS.py
skdiveMove/tests/test_TDR.py
skdiveMove/tests/test_TDRPhases.py
skdiveMove/tests/test_TDRSource.py
skdiveMove/tests/test_ZOC.py
skdiveMove/tests/test_calibrate.py
skdiveMove/tests/test_imu2body.py
skdiveMove/tests/test_imu_utils.py
skdiveMove/tests/test_imucalibrate.py
skdiveMove/tests/test_vector.py
skdiveMove/tests/data/ag_mk7_2002_022.nc
skdiveMove/tests/data/cats_temperature_calib.nc
skdiveMove/tests/data/samsung_galaxy_s5.nc
skdiveMove/tests/data/gertrude/gert_imu_frame.nc
skdiveMove/tests/data/gertrude/gert_long_srfc.csv
skdiveMove/tests/data/gertrude/magnt_accel_calib.nc
scikit_diveMove-0.4.0.dist-info/LICENSE
scikit_diveMove-0.4.0.dist-info/METADATA
scikit_diveMove-0.4.0.dist-info/WHEEL
scikit_diveMove-0.4.0.dist-info/top_level.txt
scikit_diveMove-0.4.0.dist-info/RECORD
