Metadata-Version: 2.1
Name: scikit-diveMove
Version: 0.4.0
Summary: Python interface to R package diveMove
Author-email: Sebastian Luque <spluque@gmail.com>
License: GNU AFFERO GENERAL PUBLIC LICENSE
Project-URL: Repository, https://github.com/spluque/scikit-diveMove
Keywords: animal behaviour,biology,behavioural ecology,diving,diving behaviour
Classifier: Development Status :: 4 - Beta
Classifier: Programming Language :: Python :: 3
Classifier: Intended Audience :: Developers
Classifier: Intended Audience :: Science/Research
Classifier: License :: OSI Approved :: GNU Affero General Public License v3
Classifier: Topic :: Scientific/Engineering
Requires-Python: >=3.10
License-File: LICENSE
Requires-Dist: ahrs
Requires-Dist: allantools
Requires-Dist: bottleneck
Requires-Dist: docutils >=0.3
Requires-Dist: matplotlib >=3.0
Requires-Dist: netcdf4 >=1.5
Requires-Dist: numpy >=2.0
Requires-Dist: pandas >=2.0
Requires-Dist: rpy2 >=3.5
Requires-Dist: scikit-learn >=0.20.0
Requires-Dist: scipy >=1.14
Requires-Dist: statsmodels >=0.11
Requires-Dist: xarray >=2024
Provides-Extra: dev
Requires-Dist: ipykernel >=6.20 ; extra == 'dev'
Requires-Dist: jupyter-sphinx ; extra == 'dev'
Requires-Dist: pydata-sphinx-theme ; extra == 'dev'
Provides-Extra: test
Requires-Dist: pytest ; extra == 'test'
Requires-Dist: coverage ; extra == 'test'
